pandas_redistrict-0.0.3.dist-info/DESCRIPTION.rst
pandas_redistrict-0.0.3.dist-info/METADATA
pandas_redistrict-0.0.3.dist-info/metadata.json
pandas_redistrict-0.0.3.dist-info/RECORD
pandas_redistrict-0.0.3.dist-info/top_level.txt
pandas_redistrict-0.0.3.dist-info/WHEEL
redistrict/__init__.py
redistrict/redistrict.py
redistrict/test.py
redistrict/data/.DS_Store
redistrict/data/de/.DS_Store
redistrict/data/de/12411-0014.csv
redistrict/data/de/kreise.json
redistrict/data/de/kreise_test.csv
