Metadata-Version: 2.0
Name: pandas-redistrict
Version: 0.0.3
Summary: Redistricting of pandas dataframes
Home-page: https://github.com/correctiv/pandas-redistrict
Author: Stefan Wehrmeyer
Author-email: stefan.wehrmeyer@correctiv.org
License: MIT
Platform: UNKNOWN
Classifier: Development Status :: 4 - Beta
Classifier: Intended Audience :: Science/Research
Classifier: License :: OSI Approved :: MIT License
Classifier: Natural Language :: English
Classifier: Operating System :: OS Independent
Classifier: Programming Language :: Python :: 2.7
Classifier: Topic :: Scientific/Engineering
Requires-Dist: pandas
